puc_rio_cp/__init__.py
puc_rio_cp/config.py
puc_rio_cp/downloader/__init__.py
puc_rio_cp/downloader/platforms/__init__.py
puc_rio_cp/downloader/platforms/codeforces.py
puc_rio_cp/downloader/platforms/cses.py
puc_rio_cp/downloader/platforms/kattis.py
puc_rio_cp/downloader/platforms/platform.py
puc_rio_cp/downloader/platforms/platform_manager.py
puc_rio_cp/downloader/platforms/vjudge.py
puc_rio_cp/downloader/platforms/vjudge_third_party.py
puc_rio_cp/downloader/platforms/yosupo.py
puc_rio_cp/downloader/problem_downloader.py
puc_rio_cp/downloader/problem_info.py
puc_rio_cp/downloader/server.py
puc_rio_cp/main.py
puc_rio_cp/tester/__init__.py
puc_rio_cp/tester/test.py
puc_rio_cp-0.2.4.dist-info/METADATA
puc_rio_cp-0.2.4.dist-info/WHEEL
puc_rio_cp-0.2.4.dist-info/entry_points.txt
puc_rio_cp-0.2.4.dist-info/RECORD
