Metadata-Version: 2.3
Name: puc-rio-cp
Version: 0.2.4
Summary: Competitive programming problem downloader and tester for PUC-Rio students
Author: tomytp
Author-email: thomazrebellomiranda@gmail.com
Requires-Python: >=3.10
Classifier: Programming Language :: Python :: 3
Classifier: Programming Language :: Python :: 3.10
Classifier: Programming Language :: Python :: 3.11
Classifier: Programming Language :: Python :: 3.12
Classifier: Programming Language :: Python :: 3.13
Requires-Dist: click (>=8.1.8,<9.0.0)
Requires-Dist: pydantic (>=2.10.6,<3.0.0)
